socket_burst_dampener-1.3.4.dist-info/METADATA
socket_burst_dampener-1.3.4.dist-info/WHEEL
socket_burst_dampener-1.3.4.dist-info/entry_points.txt
socket_burst_dampener-1.3.4.dist-info/licenses/LICENSE
socket_burst_dampener.py
socket_burst_dampener-1.3.4.dist-info/RECORD
