Metadata-Version: 2.4
Name: socket-burst-dampener
Version: 1.3.4
Summary: A daemon that spawns a specified command to handle each connection, and dampens connection bursts
Author-Email: Zac Medico <zmedico@gmail.com>
License-Expression: Apache-2.0
Classifier: Programming Language :: Python :: 3
Classifier: Operating System :: OS Independent
Project-URL: Homepage, https://github.com/zmedico/socket-burst-dampener
Project-URL: Bug Tracker, https://github.com/zmedico/socket-burst-dampener/issues
Requires-Python: >=3.7
